<VAST version="3.0">
  <Ad id="First">
    <InLine>
      <AdSystem>
        <![CDATA[ Adserver ]]>
      </AdSystem>
      <AdTitle>
        <![CDATA[ Demo ]]>
      </AdTitle>
    <Description>
        <![CDATA[ Inline Video Ad ]]>
    </Description>
	<Impression id="primaryAdServer">
	</Impression>
	<Creatives>
		<Creative>
			<Linear>
				<Duration>00:00:19</Duration>
				<MediaFiles>
					<MediaFile delivery="progressive" bitrate="5000000" width="1280" height="720" type="video/mp4">
						<![CDATA[ https://d31odkk8ng32e7.cloudfront.net/mp4/Broadband_TA_AVC_1920x1080_25p_EAC3_20s_ad1.mp4 ]]>
					</MediaFile>
					<MediaFile delivery="progressive" bitrate="1000000" width="640" height="480" type="video/mp4"> <!-- for smaller devices -->
						<![CDATA[ https://d31odkk8ng32e7.cloudfront.net/mp4/Broadband_TA_AVC_1920x1080_25p_EAC3_20s_ad1.mp4 ]]>
					</MediaFile>
				</MediaFiles>
				<TrackingEvents>
				</TrackingEvents>
			</Linear>
		</Creative>
	</Creatives>
    </InLine>
  </Ad>
</VAST>